unitx/__init__.py
unitx/area.py
unitx/distance.py
unitx/exceptions.py
unitx/mass.py
unitx/temperature.py
unitx/validate.py
unitx/volume.py
unitx-0.1.1.dist-info/licenses/LICENSE
unitx-0.1.1.dist-info/METADATA
unitx-0.1.1.dist-info/WHEEL
unitx-0.1.1.dist-info/top_level.txt
unitx-0.1.1.dist-info/RECORD
