Metadata-Version: 2.4
Name: unitx
Version: 0.1.1
Summary: A Python library which dynamically converts different types of units
Author-email: devs_des1re <arjunbrij8811@gmail.com>
Maintainer-email: devs_des1re <arjunbrij8811@gmail.com>
License: Copyright (c) 2025 devs_des1re
Project-URL: Homepage, https://github.com/devs-des1re/unitx
Project-URL: Issues, https://github.com/devs-des1re/unitx/issues
Project-URL: Documentation, https://unitx.readthedocs.io/en/stable
Keywords: app,macOS,windows,linux,flatpak
Classifier: Development Status :: 4 - Beta
Classifier: Intended Audience :: Developers
Classifier: Operating System :: OS Independent
Classifier: Programming Language :: Python :: 3
Classifier: Programming Language :: Python :: 3.10
Classifier: Programming Language :: Python :: 3.11
Classifier: Programming Language :: Python :: 3.12
Classifier: Programming Language :: Python :: 3.13
Classifier: Programming Language :: Python :: 3.14
Classifier: Programming Language :: Python :: 3 :: Only
Classifier: Topic :: Software Development
Classifier: Topic :: Utilities
Requires-Python: >=3.10
License-File: LICENSE
Dynamic: license-file
